eda_report/__init__.py
eda_report/__main__.py
eda_report/_analysis.py
eda_report/_cli.py
eda_report/_content.py
eda_report/_read_file.py
eda_report/_validate.py
eda_report/bivariate.py
eda_report/document.py
eda_report/exceptions.py
eda_report/gui.py
eda_report/plotting.py
eda_report/univariate.py
eda_report/images/background.png
eda_report/images/icon.png
eda_report-2.8.2.dist-info/LICENSE
eda_report-2.8.2.dist-info/METADATA
eda_report-2.8.2.dist-info/WHEEL
eda_report-2.8.2.dist-info/entry_points.txt
eda_report-2.8.2.dist-info/top_level.txt
eda_report-2.8.2.dist-info/RECORD
