Metadata-Version: 2.1
Name: eda_report
Version: 2.8.2
Summary: Automate exploratory data analysis and reporting.
Home-page: https://eda-report.readthedocs.io/
Author: Abwao
Author-email: abwaomusungu@gmail.com
License: MIT
Project-URL: Source Code, https://github.com/Tim-Abwao/eda-report
Keywords: eda exploratory data analysis report
Classifier: Development Status :: 4 - Beta
Classifier: Intended Audience :: Science/Research
Classifier: License :: OSI Approved :: MIT License
Classifier: Operating System :: OS Independent
Classifier: Programming Language :: Python :: 3.12
Requires-Python: >=3.10
License-File: LICENSE
Requires-Dist: matplotlib>=3.10.0
Requires-Dist: openpyxl>=3.1.5
Requires-Dist: pandas>=2.2.3
Requires-Dist: python-docx>=1.1.2
Requires-Dist: scipy>=1.14.1
Requires-Dist: tqdm>=4.67.1
Provides-Extra: dev
Requires-Dist: black>=24.10.0; extra == "dev"
Requires-Dist: coverage>=7.6.10; extra == "dev"
Requires-Dist: flake8>=7.1.1; extra == "dev"
Requires-Dist: pytest>=8.3.4; extra == "dev"
